infinity/__init__.py
infinity.py-1.0.0.dist-info/LICENSE
infinity.py-1.0.0.dist-info/METADATA
infinity.py-1.0.0.dist-info/WHEEL
infinity.py-1.0.0.dist-info/top_level.txt
infinity.py-1.0.0.dist-info/RECORD
