Metadata-Version: 2.1
Name: infinity.py
Version: 1.0.0
Summary: Library for Infinity
Home-page: UNKNOWN
Author: Minori
Author-email: minorigithub@gmail.com
License: MIT
Keywords: tda,infinity,infinity.py,infinity-bot,api,python,python3,python3.x,minori
Platform: UNKNOWN
Requires-Python: >=3.6
License-File: LICENSE
Requires-Dist: requests
Requires-Dist: json-minify
Requires-Dist: six
